source_amazon_seller_partner/__init__.py
source_amazon_seller_partner/components/__init__.py
source_amazon_seller_partner/components/auth.py
source_amazon_seller_partner/components/backoff_strategy.py
source_amazon_seller_partner/components/decoder.py
source_amazon_seller_partner/components/type_transformers.py
source_amazon_seller_partner/config_migrations.py
source_amazon_seller_partner/constants.py
source_amazon_seller_partner/manifest.yaml
source_amazon_seller_partner/run.py
source_amazon_seller_partner/schemas/GET_AFN_INVENTORY_DATA.json
source_amazon_seller_partner/schemas/GET_AFN_INVENTORY_DATA_BY_COUNTRY.json
source_amazon_seller_partner/schemas/GET_AMAZON_FULFILLED_SHIPMENTS_DATA_GENERAL.json
source_amazon_seller_partner/schemas/GET_FBA_ESTIMATED_FBA_FEES_TXT_DATA.json
source_amazon_seller_partner/schemas/GET_FBA_FULFILLMENT_CUSTOMER_RETURNS_DATA.json
source_amazon_seller_partner/schemas/GET_FBA_FULFILLMENT_CUSTOMER_SHIPMENT_PROMOTION_DATA.json
source_amazon_seller_partner/schemas/GET_FBA_FULFILLMENT_CUSTOMER_SHIPMENT_REPLACEMENT_DATA.json
source_amazon_seller_partner/schemas/GET_FBA_FULFILLMENT_REMOVAL_ORDER_DETAIL_DATA.json
source_amazon_seller_partner/schemas/GET_FBA_FULFILLMENT_REMOVAL_SHIPMENT_DETAIL_DATA.json
source_amazon_seller_partner/schemas/GET_FBA_INVENTORY_PLANNING_DATA.json
source_amazon_seller_partner/schemas/GET_FBA_MYI_UNSUPPRESSED_INVENTORY_DATA.json
source_amazon_seller_partner/schemas/GET_FBA_REIMBURSEMENTS_DATA.json
source_amazon_seller_partner/schemas/GET_FBA_SNS_FORECAST_DATA.json
source_amazon_seller_partner/schemas/GET_FBA_SNS_PERFORMANCE_DATA.json
source_amazon_seller_partner/schemas/GET_FBA_STORAGE_FEE_CHARGES_DATA.json
source_amazon_seller_partner/schemas/GET_FLAT_FILE_ACTIONABLE_ORDER_DATA_SHIPPING.json
source_amazon_seller_partner/schemas/GET_FLAT_FILE_ALL_ORDERS_DATA_BY_LAST_UPDATE_GENERAL.json
source_amazon_seller_partner/schemas/GET_FLAT_FILE_ALL_ORDERS_DATA_BY_ORDER_DATE_GENERAL.json
airbyte_source_amazon_seller_partner-4.6.4.dist-info/METADATA
airbyte_source_amazon_seller_partner-4.6.4.dist-info/WHEEL
airbyte_source_amazon_seller_partner-4.6.4.dist-info/entry_points.txt
airbyte_source_amazon_seller_partner-4.6.4.dist-info/RECORD
