Metadata-Version: 2.3
Name: airbyte-source-amazon-seller-partner
Version: 4.6.4
Summary: Source implementation for Amazon Seller Partner.
License: MIT
Author: Airbyte
Author-email: contact@airbyte.io
Requires-Python: >=3.10,<3.12
Classifier: License :: OSI Approved :: MIT License
Classifier: Programming Language :: Python :: 3
Classifier: Programming Language :: Python :: 3.10
Classifier: Programming Language :: Python :: 3.11
Requires-Dist: airbyte-cdk (==6.36.2)
Requires-Dist: dateparser (==1.2.0)
Requires-Dist: pendulum (<3.0.0)
Requires-Dist: xmltodict (>=0.12,<1.0)
Project-URL: Documentation, https://docs.airbyte.com/integrations/sources/amazon-seller-partner
Project-URL: Homepage, https://airbyte.com
Project-URL: Repository, https://github.com/airbytehq/airbyte
